split_manga_pages/__init__.py
split_manga_pages/split_manga_pages.py
split_manga_pages/utils.py
split_manga_pages-0.1.1.dist-info/LICENSE
split_manga_pages-0.1.1.dist-info/METADATA
split_manga_pages-0.1.1.dist-info/WHEEL
split_manga_pages-0.1.1.dist-info/entry_points.txt
split_manga_pages-0.1.1.dist-info/top_level.txt
split_manga_pages-0.1.1.dist-info/RECORD
