Metadata-Version: 2.1
Name: split_manga_pages
Version: 0.1.1
Summary: Split double page layout manga images into single page layout
Home-page: https://github.com/christofferaakre/split_manga_pages
Author: Christoffer Aakre
Author-email: christoffer.corfield@gmail.com
License: UNKNOWN
Project-URL: Bug Tracker, https://github.com/christofferaakre/split_manga_pages/issues
Platform: UNKNOWN
Classifier: Programming Language :: Python :: 3
Classifier: License :: OSI Approved :: GNU General Public License v3 or later (GPLv3+)
Classifier: Operating System :: OS Independent
Requires-Python: >=3.6
License-File: LICENSE
